onnxruntime/__init__.py
onnxruntime/Privacy.md
onnxruntime/LICENSE
onnxruntime/ThirdPartyNotices.txt
onnxruntime/capi/__init__.py
onnxruntime/capi/onnxruntime_pybind11_state.cpython-38-x86_64-linux-gnu.so
onnxruntime/capi/pt_patch.py
onnxruntime/capi/_ld_preload.py
onnxruntime/capi/ort_trainer.py
onnxruntime/capi/onnxruntime_validation.py
onnxruntime/capi/checkpointing_utils.py
onnxruntime/capi/onnxruntime_inference_collection.py
onnxruntime/capi/_pybind_state.py
onnxruntime/capi/training/__init__.py
onnxruntime/capi/training/training_session.py
onnxruntime/training/register_custom_ops_pytorch_exporter.py
onnxruntime/training/postprocess.py
onnxruntime/training/__init__.py
onnxruntime/training/model_desc_validation.py
onnxruntime/training/ortmodule.py
onnxruntime/training/training_agent.py
onnxruntime/training/orttrainer_options.py
onnxruntime/training/_ortmodule_output_transformation.py
onnxruntime/training/_utils.py
onnxruntime/training/orttrainer.py
onnxruntime/training/checkpoint.py
onnxruntime/training/_checkpoint_storage.py
onnxruntime/training/amp/__init__.py
onnxruntime/training/amp/loss_scaler.py
onnxruntime/training/optim/lr_scheduler.py
onnxruntime/training/optim/__init__.py
onnxruntime/training/optim/config.py
onnxruntime/tools/__init__.py
onnxruntime/tools/symbolic_shape_infer.py
onnxruntime/tools/onnxruntime_test.py
onnxruntime/transformers/huggingface_models.py
onnxruntime/transformers/convert_tf_models_to_pytorch.py
onnxruntime/transformers/fusion_gelu_approximation.py
onnxruntime/transformers/fusion_embedlayer.py
onnxruntime/transformers/benchmark_gpt2.py
onnxruntime/transformers/machine_info.py
onnxruntime/transformers/gpt2_helper.py
onnxruntime/transformers/fusion_gpt_attention_no_past.py
onnxruntime/transformers/__init__.py
onnxruntime/transformers/fusion_reshape.py
onnxruntime/transformers/onnx_model.py
onnxruntime/transformers/fusion_base.py
onnxruntime/transformers/shape_optimizer.py
ort_gpu_nightly_training-1.7.0.dev202103145.dist-info/WHEEL
ort_gpu_nightly_training-1.7.0.dev202103145.dist-info/METADATA
ort_gpu_nightly_training-1.7.0.dev202103145.dist-info/RECORD
ort_gpu_nightly_training-1.7.0.dev202103145.dist-info/entry_points.txt
ort_gpu_nightly_training-1.7.0.dev202103145.dist-info/top_level.txt
